{
    "os": "Linux-6.6.19-1-MANJARO-x86_64-with-glibc2.39",
    "python": "3.11.7",
    "heartbeatAt": "2024-03-15T14:03:09.989276",
    "startedAt": "2024-03-15T14:03:09.482768",
    "docker": null,
    "cuda": null,
    "args": [],
    "state": "running",
    "program": "/home/liamo/Vscode/FYP_PokemonRed_RL/run_baseline_v2.py",
    "codePathLocal": "run_baseline_v2.py",
    "codePath": "run_baseline_v2.py",
    "git": {
        "remote": "git@github.com:liamo3323/FYP_PokemonRed_RL.git",
        "commit": "1fee01d2e0403b1791db8a9710dbad1a36a11cb4"
    },
    "email": "liam3323@gmail.com",
    "root": "/home/liamo/Vscode/FYP_PokemonRed_RL",
    "host": "re-manjaro",
    "username": "liamo",
    "executable": "/home/liamo/Vscode/FYP_PokemonRed_RL/.venv/bin/python",
    "cpu_count": 8,
    "cpu_count_logical": 16,
    "cpu_freq": {
        "current": 5029.102625,
        "min": 400.0,
        "max": 5573.0
    },
    "cpu_freq_per_core": [
        {
            "current": 3585.424,
            "min": 400.0,
            "max": 5573.0
        },
        {
            "current": 5252.097,
            "min": 400.0,
            "max": 5573.0
        },
        {
            "current": 5049.189,
            "min": 400.0,
            "max": 5573.0
        },
        {
            "current": 5250.771,
            "min": 400.0,
            "max": 5573.0
        },
        {
            "current": 5250.696,
            "min": 400.0,
            "max": 5573.0
        },
        {
            "current": 5252.137,
            "min": 400.0,
            "max": 5573.0
        },
        {
            "current": 5247.089,
            "min": 400.0,
            "max": 5573.0
        },
        {
            "current": 5244.415,
            "min": 400.0,
            "max": 5573.0
        },
        {
            "current": 4089.063,
            "min": 400.0,
            "max": 5573.0
        },
        {
            "current": 5254.131,
            "min": 400.0,
            "max": 5573.0
        },
        {
            "current": 4743.448,
            "min": 400.0,
            "max": 5573.0
        },
        {
            "current": 5258.853,
            "min": 400.0,
            "max": 5573.0
        },
        {
            "current": 5202.533,
            "min": 400.0,
            "max": 5573.0
        },
        {
            "current": 5271.111,
            "min": 400.0,
            "max": 5573.0
        },
        {
            "current": 5250.374,
            "min": 400.0,
            "max": 5573.0
        },
        {
            "current": 5264.311,
            "min": 400.0,
            "max": 5573.0
        }
    ],
    "disk": {
        "/": {
            "total": 457.0881042480469,
            "used": 264.39163970947266
        }
    },
    "gpu": "NVIDIA GeForce RTX 4070 Ti",
    "gpu_count": 1,
    "gpu_devices": [
        {
            "name": "NVIDIA GeForce RTX 4070 Ti",
            "memory_total": 12878610432
        }
    ],
    "memory": {
        "total": 61.96844482421875
    }
}
